odoo/addons/account_cutoff_start_end_dates/README.rst
odoo/addons/account_cutoff_start_end_dates/__init__.py
odoo/addons/account_cutoff_start_end_dates/__manifest__.py
odoo/addons/account_cutoff_start_end_dates/hooks.py
odoo/addons/account_cutoff_start_end_dates/i18n/account_cutoff_prepaid.pot
odoo/addons/account_cutoff_start_end_dates/i18n/account_cutoff_start_end_dates.pot
odoo/addons/account_cutoff_start_end_dates/i18n/am.po
odoo/addons/account_cutoff_start_end_dates/i18n/ar.po
odoo/addons/account_cutoff_start_end_dates/i18n/da.po
odoo/addons/account_cutoff_start_end_dates/i18n/de.po
odoo/addons/account_cutoff_start_end_dates/i18n/el_GR.po
odoo/addons/account_cutoff_start_end_dates/i18n/es.po
odoo/addons/account_cutoff_start_end_dates/i18n/es_CO.po
odoo/addons/account_cutoff_start_end_dates/i18n/es_ES.po
odoo/addons/account_cutoff_start_end_dates/i18n/es_MX.po
odoo/addons/account_cutoff_start_end_dates/i18n/fi.po
odoo/addons/account_cutoff_start_end_dates/i18n/fr.po
odoo/addons/account_cutoff_start_end_dates/i18n/fr_FR.po
odoo/addons/account_cutoff_start_end_dates/i18n/hr.po
odoo/addons/account_cutoff_start_end_dates/i18n/hr_HR.po
odoo/addons/account_cutoff_start_end_dates/i18n/it.po
odoo/addons/account_cutoff_start_end_dates/i18n/nb.po
odoo/addons/account_cutoff_start_end_dates/i18n/nb_NO.po
odoo/addons/account_cutoff_start_end_dates/i18n/nl.po
odoo/addons/account_cutoff_start_end_dates/i18n/nl_BE.po
odoo/addons/account_cutoff_start_end_dates/i18n/nl_NL.po
odoo/addons/account_cutoff_start_end_dates/i18n/pt.po
odoo/addons/account_cutoff_start_end_dates/i18n/pt_BR.po
odoo/addons/account_cutoff_start_end_dates/i18n/ro.po
odoo/addons/account_cutoff_start_end_dates/i18n/sk.po
odoo/addons/account_cutoff_start_end_dates/i18n/sl.po
odoo/addons/account_cutoff_start_end_dates/i18n/tr.po
odoo/addons/account_cutoff_start_end_dates/i18n/zh_CN.po
odoo/addons/account_cutoff_start_end_dates/images/prepaid_revenue_done.jpg
odoo14_addon_account_cutoff_start_end_dates-14.0.1.1.0.dist-info/METADATA
odoo14_addon_account_cutoff_start_end_dates-14.0.1.1.0.dist-info/WHEEL
odoo14_addon_account_cutoff_start_end_dates-14.0.1.1.0.dist-info/top_level.txt
odoo14_addon_account_cutoff_start_end_dates-14.0.1.1.0.dist-info/RECORD
